BUGS.txt
CHANGES.txt
COPYRIGHT.txt
LICENSE.txt
MANIFEST.in
README.txt
setup.cfg
setup.py
docs/Makefile
docs/bugs.rst
docs/changes.rst
docs/conf.py
docs/index.rst
docs/model_examples.rst
docs/non_database_features.rst
docs/usage.rst
docs/_static/default.css
pyramid_sqla/__init__.py
pyramid_sqla/static.py
pyramid_sqla.egg-info/PKG-INFO
pyramid_sqla.egg-info/SOURCES.txt
pyramid_sqla.egg-info/dependency_links.txt
pyramid_sqla.egg-info/entry_points.txt
pyramid_sqla.egg-info/not-zip-safe
pyramid_sqla.egg-info/requires.txt
pyramid_sqla.egg-info/top_level.txt
pyramid_sqla/paster_templates/__init__.py
pyramid_sqla/paster_templates/pyramid_sqla/CHANGES.txt_tmpl
pyramid_sqla/paster_templates/pyramid_sqla/README.txt_tmpl
pyramid_sqla/paster_templates/pyramid_sqla/development.ini_tmpl
pyramid_sqla/paster_templates/pyramid_sqla/development.ini_tmpl_commit_veto
pyramid_sqla/paster_templates/pyramid_sqla/setup.cfg_tmpl
pyramid_sqla/paster_templates/pyramid_sqla/setup.py_tmpl
pyramid_sqla/paster_templates/pyramid_sqla/setup.py_tmpl_commit_veto
pyramid_sqla/paster_templates/pyramid_sqla/+package+/__init__.py_tmpl
pyramid_sqla/paster_templates/pyramid_sqla/+package+/handlers.py_tmpl
pyramid_sqla/paster_templates/pyramid_sqla/+package+/helpers.py
pyramid_sqla/paster_templates/pyramid_sqla/+package+/models.py
pyramid_sqla/paster_templates/pyramid_sqla/+package+/subscribers.py_tmpl
pyramid_sqla/paster_templates/pyramid_sqla/+package+/tests.py_tmpl
pyramid_sqla/paster_templates/pyramid_sqla/+package+/websetup.py_tmpl
pyramid_sqla/paster_templates/pyramid_sqla/+package+/scripts/__init__.py
pyramid_sqla/paster_templates/pyramid_sqla/+package+/scripts/create_db.py_tmpl
pyramid_sqla/paster_templates/pyramid_sqla/+package+/static/favicon.ico
pyramid_sqla/paster_templates/pyramid_sqla/+package+/static/images/logo.png
pyramid_sqla/paster_templates/pyramid_sqla/+package+/static/stylesheets/pylons.css
pyramid_sqla/paster_templates/pyramid_sqla/+package+/templates/index.html
pyramid_sqla/tests/__init__.py
pyramid_sqla/tests/test.py