Metadata-Version: 1.0
Name: pyramid-sqla
Version: 0.2
Summary: A SQLAlchemy library and Pylons-like application template for Pyramid
Home-page: http://docs.pylonshq.com
Author: Mike Orr
Author-email: sluggoster@gmail.com
License: BSD-derived (http://www.repoze.org/LICENSE.txt)
Keywords: web wsgi pylons pyramid
Platform: UNKNOWN
Classifier: Intended Audience :: Developers
Classifier: Framework :: Pylons
Classifier: Programming Language :: Python
